ddbclient/__init__.py
ddbclient/acquisition.py
ddbclient/base.py
ddbclient/client.py
ddbclient/section.py
ddbclient/session.py
ddbclient/specimen.py
ddbclient/utils.py
ddbclient-0.0.2.dist-info/LICENSE
ddbclient-0.0.2.dist-info/METADATA
ddbclient-0.0.2.dist-info/WHEEL
ddbclient-0.0.2.dist-info/top_level.txt
ddbclient-0.0.2.dist-info/RECORD
