Metadata-Version: 2.1
Name: ddbclient
Version: 0.0.2
Summary: A wrapper for API calls to DispimDB
Home-page: https://github.com/AllenInstitute/dispimdb
Author: Sam Kinn, Russel Torres
Author-email: samrkinn@gmail.com
License: UNKNOWN
Platform: UNKNOWN
Requires-Dist: imageio
Requires-Dist: numpy
Requires-Dist: requests
Requires-Dist: uri-handler
